sphinx_github_role/__init__.py
sphinx_github_role-0.1.0.dist-info/WHEEL
sphinx_github_role-0.1.0.dist-info/METADATA
sphinx_github_role-0.1.0.dist-info/RECORD
