Metadata-Version: 2.1
Name: sphinx-github-role
Version: 0.1.0
Summary: sphinx-github-role
Author-email: Juan Luis Cano Rodríguez <hello@juanlu.space>
Classifier: Development Status :: 3 - Alpha
Classifier: Environment :: Console
Classifier: Environment :: Web Environment
Classifier: Framework :: Sphinx :: Extension
Classifier: Intended Audience :: Developers
Classifier: License :: OSI Approved :: BSD License
Classifier: Operating System :: OS Independent
Classifier: Programming Language :: Python
Classifier: Programming Language :: Python :: 3
Classifier: Programming Language :: Python :: 3.7
Classifier: Programming Language :: Python :: 3.8
Classifier: Programming Language :: Python :: 3.9
Classifier: Topic :: Documentation
Classifier: Topic :: Documentation :: Sphinx
Classifier: Topic :: Utilities
Requires-Dist: furo ; extra == "dev"
Requires-Dist: hypothesis ; extra == "dev"
Requires-Dist: myst-parser ; extra == "dev"
Requires-Dist: pytest ; extra == "dev"
Requires-Dist: pytest-cov ; extra == "dev"
Requires-Dist: pytest-mypy ; extra == "dev"
Requires-Dist: sphinx ; extra == "dev"
Requires-Dist: furo ; extra == "doc"
Requires-Dist: myst-parser ; extra == "doc"
Requires-Dist: sphinx~=4.3.0 ; extra == "doc"
Project-URL: documentation, https://sphinx-github-role.readthedocs.io
Project-URL: source, https://github.com/astrojuanlu/sphinx-github-role
Project-URL: tracker, https://github.com/astrojuanlu/sphinx-github-role/issues
Provides-Extra: dev
Provides-Extra: doc
